{"cameraMode":{"drawMode":0,"name":"Shaded","section":"Shading Mode"},"sceneLighting":false,"audioPlay":false,"sceneViewState":{"showFog":false,"showMaterialUpdate":false,"showSkybox":false,"showFlares":false,"showImageEffects":false,"showParticleSystems":false,"showVisualEffectGraphs":false,"m_FxEnabled":true},"in2DMode":false,"pivot":{"x":0.4227370619773865,"y":0.32452431321144106,"z":0.5369570851325989},"rotation":{"x":8.165836362650225e-8,"y":0.8737697601318359,"z":3.2752062395502438e-8,"w":0.4863418638706207},"size":0.6764401197433472,"orthographic":false}